<?xml version="1.0" encoding="UTF-8"?>
<!DOCTYPE mapper PUBLIC "-//mybatis.org//DTD Mapper 3.0//EN" "http://mybatis.org/dtd/mybatis-3-mapper.dtd">
<mapper namespace="org.lint.DAO.EcsUserAddressMapper">
  <resultMap id="BaseResultMap" type="org.lint.Entity.EcsUserAddress">
    <!--
      WARNING - @mbg.generated
      This element is automatically generated by MyBatis Generator, do not modify.
    -->
    <id column="address_id" jdbcType="INTEGER" property="addressId" />
    <result column="address_name" jdbcType="VARCHAR" property="addressName" />
    <result column="user_id" jdbcType="INTEGER" property="userId" />
    <result column="consignee" jdbcType="VARCHAR" property="consignee" />
    <result column="email" jdbcType="VARCHAR" property="email" />
    <result column="country" jdbcType="SMALLINT" property="country" />
    <result column="province" jdbcType="SMALLINT" property="province" />
    <result column="city" jdbcType="SMALLINT" property="city" />
    <result column="district" jdbcType="SMALLINT" property="district" />
    <result column="address" jdbcType="VARCHAR" property="address" />
    <result column="zipcode" jdbcType="VARCHAR" property="zipcode" />
    <result column="tel" jdbcType="VARCHAR" property="tel" />
    <result column="mobile" jdbcType="VARCHAR" property="mobile" />
    <result column="sign_building" jdbcType="VARCHAR" property="signBuilding" />
    <result column="best_time" jdbcType="VARCHAR" property="bestTime" />
  </resultMap>
  <delete id="deleteByPrimaryKey" parameterType="java.lang.Integer">
    <!--
      WARNING - @mbg.generated
      This element is automatically generated by MyBatis Generator, do not modify.
    -->
    delete from ecs_user_address
    where address_id = #{addressId,jdbcType=INTEGER}
  </delete>
  <insert id="insert" parameterType="org.lint.Entity.EcsUserAddress">
    <!--
      WARNING - @mbg.generated
      This element is automatically generated by MyBatis Generator, do not modify.
    -->
    insert into ecs_user_address (address_id, address_name, user_id, 
      consignee, email, country, 
      province, city, district, 
      address, zipcode, tel, 
      mobile, sign_building, best_time
      )
    values (#{addressId,jdbcType=INTEGER}, #{addressName,jdbcType=VARCHAR}, #{userId,jdbcType=INTEGER}, 
      #{consignee,jdbcType=VARCHAR}, #{email,jdbcType=VARCHAR}, #{country,jdbcType=SMALLINT}, 
      #{province,jdbcType=SMALLINT}, #{city,jdbcType=SMALLINT}, #{district,jdbcType=SMALLINT}, 
      #{address,jdbcType=VARCHAR}, #{zipcode,jdbcType=VARCHAR}, #{tel,jdbcType=VARCHAR}, 
      #{mobile,jdbcType=VARCHAR}, #{signBuilding,jdbcType=VARCHAR}, #{bestTime,jdbcType=VARCHAR}
      )
  </insert>
  <update id="updateByPrimaryKey" parameterType="org.lint.Entity.EcsUserAddress">
    <!--
      WARNING - @mbg.generated
      This element is automatically generated by MyBatis Generator, do not modify.
    -->
    update ecs_user_address
    set address_name = #{addressName,jdbcType=VARCHAR},
      user_id = #{userId,jdbcType=INTEGER},
      consignee = #{consignee,jdbcType=VARCHAR},
      email = #{email,jdbcType=VARCHAR},
      country = #{country,jdbcType=SMALLINT},
      province = #{province,jdbcType=SMALLINT},
      city = #{city,jdbcType=SMALLINT},
      district = #{district,jdbcType=SMALLINT},
      address = #{address,jdbcType=VARCHAR},
      zipcode = #{zipcode,jdbcType=VARCHAR},
      tel = #{tel,jdbcType=VARCHAR},
      mobile = #{mobile,jdbcType=VARCHAR},
      sign_building = #{signBuilding,jdbcType=VARCHAR},
      best_time = #{bestTime,jdbcType=VARCHAR}
    where address_id = #{addressId,jdbcType=INTEGER}
  </update>
  <select id="selectByPrimaryKey" parameterType="java.lang.Integer" resultMap="BaseResultMap">
    <!--
      WARNING - @mbg.generated
      This element is automatically generated by MyBatis Generator, do not modify.
    -->
    select address_id, address_name, user_id, consignee, email, country, province, city, 
    district, address, zipcode, tel, mobile, sign_building, best_time
    from ecs_user_address
    where address_id = #{addressId,jdbcType=INTEGER}
  </select>
  <select id="selectAll" resultMap="BaseResultMap">
    <!--
      WARNING - @mbg.generated
      This element is automatically generated by MyBatis Generator, do not modify.
    -->
    select address_id, address_name, user_id, consignee, email, country, province, city, 
    district, address, zipcode, tel, mobile, sign_building, best_time
    from ecs_user_address
  </select>
</mapper>